duckingit/__init__.py
duckingit/_config.py
duckingit/_controller.py
duckingit/_dataset.py
duckingit/_exceptions.py
duckingit/_parser.py
duckingit/_planner.py
duckingit/_session.py
duckingit/_utils.py
duckingit/integrations/__init__.py
duckingit/providers/__init__.py
duckingit/providers/aws.py
duckingit/providers/provider.py
duckingit-0.0.11.dist-info/LICENSE
duckingit-0.0.11.dist-info/METADATA
duckingit-0.0.11.dist-info/WHEEL
duckingit-0.0.11.dist-info/top_level.txt
duckingit-0.0.11.dist-info/RECORD
