Metadata-Version: 2.1
Name: duckingit
Version: 0.0.11
Summary: A framework to leverage clusters of serverless functions for analytics. Powered by DuckDB
Author-email: Tobias Egelund <egelundtobias@gmail.com>
Project-URL: Homepage, https://github.com/tobiasegelund/duckingit
Project-URL: Bug Tracker, https://github.com/tobiasegelund/duckingit/issues
Keywords: Serverless,DuckDB,Data Engineering
Classifier: Programming Language :: Python :: 3
Classifier: License :: OSI Approved :: MIT License
Classifier: Operating System :: OS Independent
Requires-Python: >=3.10
License-File: LICENSE
Requires-Dist: boto3
Requires-Dist: duckdb
Requires-Dist: sqlglot (<12.0)
Requires-Dist: pyarrow
